zmq_rpc/__init__.py
zmq_rpc/base.py
zmq_rpc/client.py
zmq_rpc/errors.py
zmq_rpc/packer.py
zmq_rpc/server.py
zmq_rpc-1.0.1.dist-info/METADATA
zmq_rpc-1.0.1.dist-info/RECORD
zmq_rpc-1.0.1.dist-info/WHEEL
zmq_rpc-1.0.1.dist-info/top_level.txt
