Metadata-Version: 2.1
Name: zmq-rpc
Version: 1.0.1
Summary: 0mq RPC calls implemented with pyzmq.
Home-page: http://odoo.consulting
Author: XCG Consulting
Author-email: contact@xcg-consulting.fr
License: UNKNOWN
Keywords: zmq rpc msgpack
Platform: UNKNOWN
Classifier: Programming Language :: Python
Requires-Dist: msgpack
Requires-Dist: pyzmq
